{
  "token_name": "Terraform08193",
  "land_type": "Grass",
  "pool_link": "https://pool.pm/c859e9d7e71b8f90bdc1e453fd1b9adbc5e6163898fb574543cb5be8.Terraform08193",
  "image": "https://ipfs.blockfrost.dev/ipfs/QmZvYY9gYbDf3GRHxLfsRyboWr28iFR8EH3pjT3HDW18ES",
  "alpha_sector": "Asama",
  "activity": "None",
  "atmosphere": "Custodial_Nanites",
  "bunker": "None",
  "fauna": "None",
  "forests": "Evergreen",
  "hazardous_flora": "Giant_Mantrap",
  "lithoglyphs": "Lithoglyphs_Blue",
  "power_level": 2,
  "quantum_flux": 3,
  "primary_minerals": "Cardanium",
  "secondary_minerals": "Gemstones",
  "ruins": "None",
  "shrine": "None",
  "water": "Freshwater_Lake",
  "location": {
    "x": 15,
    "y": 97
  }
}