{
  "token_name": "Terraform02889",
  "land_type": "Rocky",
  "pool_link": "https://pool.pm/c859e9d7e71b8f90bdc1e453fd1b9adbc5e6163898fb574543cb5be8.Terraform02889",
  "image": "https://ipfs.blockfrost.dev/ipfs/QmPsGPPz6S73b55qv8RJW8LiZhc5jJwDKf89yV5j871gDa",
  "alpha_sector": "Asama",
  "activity": "None",
  "atmosphere": "None",
  "bunker": "None",
  "fauna": "Ultrasaurs",
  "forests": "Prismaleaf",
  "hazardous_flora": "Common_Hydra",
  "lithoglyphs": "Lithoglyphs_Blue",
  "power_level": 6,
  "quantum_flux": 5,
  "primary_minerals": "None",
  "secondary_minerals": "None",
  "ruins": "None",
  "shrine": "None",
  "water": "Freshwater_Lake",
  "location": {
    "x": 63,
    "y": 69
  }
}