{
  "token_name": "Terraform09243",
  "land_type": "Grass",
  "pool_link": "https://pool.pm/c859e9d7e71b8f90bdc1e453fd1b9adbc5e6163898fb574543cb5be8.Terraform09243",
  "image": "https://ipfs.blockfrost.dev/ipfs/QmVEcoWB5ZxpqrtC8RCAXesuQEzMpmXWT26Bu72hSSA4wh",
  "alpha_sector": "Arshi_En",
  "activity": "None",
  "atmosphere": "Custodial_Nanites",
  "bunker": "Reinforced_Bunker",
  "fauna": "None",
  "forests": "Evergreen",
  "hazardous_flora": "Fungal_Hydra",
  "lithoglyphs": "Lithoglyphs_Green",
  "power_level": 5,
  "quantum_flux": 9,
  "primary_minerals": "Radium",
  "secondary_minerals": "Fossils",
  "ruins": "None",
  "shrine": "Fungal_Shrine",
  "water": "Saltwater_Lake",
  "location": {
    "x": 46,
    "y": 40
  }
}