{
  "token_name": "Terraform09238",
  "land_type": "Wasteland",
  "pool_link": "https://pool.pm/c859e9d7e71b8f90bdc1e453fd1b9adbc5e6163898fb574543cb5be8.Terraform09238",
  "image": "https://ipfs.blockfrost.dev/ipfs/QmYcS5wQUZYfVYXpcZPcfyoxFVcFeSDkCXoigTdj31rGmW",
  "alpha_sector": "Arshi_En",
  "activity": "None",
  "atmosphere": "None",
  "bunker": "None",
  "fauna": "Livestock",
  "forests": "Palms",
  "hazardous_flora": "Common_Hydra",
  "lithoglyphs": "Lithoglyphs_Blue",
  "power_level": 3,
  "quantum_flux": 6,
  "primary_minerals": "Iron",
  "secondary_minerals": "None",
  "ruins": "None",
  "shrine": "None",
  "water": "Freshwater_Lake",
  "location": {
    "x": 15,
    "y": 33
  },
  "neighbors": {
    "top": {
      "x": 15,
      "y": 34
    },
    "topRight": {
      "x": 16,
      "y": 34
    },
    "right": {
      "x": 16,
      "y": 33
    },
    "bottomRight": {
      "x": 16,
      "y": 32
    },
    "bottom": {
      "x": 15,
      "y": 32
    },
    "bottonLeft": {
      "x": 14,
      "y": 32
    },
    "left": {
      "x": 14,
      "y": 33
    },
    "topLeft": {
      "x": 14,
      "y": 34
    }
  }
}