{
  "token_name": "Terraform02068",
  "land_type": "Rocky",
  "pool_link": "https://pool.pm/c859e9d7e71b8f90bdc1e453fd1b9adbc5e6163898fb574543cb5be8.Terraform02068",
  "image": "https://ipfs.blockfrost.dev/ipfs/QmTYswiYk4gCMP4XmmL2CYQ3mVj4KdZCgBG2pTLqWX4Pxz",
  "alpha_sector": "Asama",
  "activity": "Magnetic_Activity",
  "atmosphere": "Prismatic_Motes",
  "bunker": "Cardanium_Bunker",
  "fauna": "None",
  "forests": "Prismaleaf",
  "hazardous_flora": "Common_Hydra",
  "lithoglyphs": "Lithoglyphs_Orange",
  "power_level": 3,
  "quantum_flux": 7,
  "primary_minerals": "Iron",
  "secondary_minerals": "None",
  "ruins": "Alien_Technology_Blue",
  "shrine": "Fungal_Shrine",
  "water": "Funky_Lake",
  "location": {
    "x": 65,
    "y": 43
  }
}