{
  "token_name": "Terraform17213",
  "land_type": "Wasteland",
  "pool_link": "https://pool.pm/c859e9d7e71b8f90bdc1e453fd1b9adbc5e6163898fb574543cb5be8.Terraform17213",
  "image": "https://ipfs.blockfrost.dev/ipfs/QmUZVM8KzWiQhCNBA1pt8VHL23rY4JjB8Amse6NiX9V4w7",
  "alpha_sector": "Asama",
  "activity": "None",
  "atmosphere": "Fungal_Spores",
  "bunker": "Quantum_Reinforced_Bunker",
  "fauna": "None",
  "forests": "Palms",
  "hazardous_flora": "None",
  "lithoglyphs": "Lithoglyphs_Orange",
  "power_level": 1,
  "quantum_flux": 6,
  "primary_minerals": "Radium",
  "secondary_minerals": "None",
  "ruins": "Ancient_Ruins",
  "shrine": "Fungal_Shrine",
  "water": "Saltwater_Lake",
  "location": {
    "x": 5,
    "y": 17
  }
}