{
  "token_name": "Terraform19196",
  "land_type": "Tundra",
  "pool_link": "https://pool.pm/c859e9d7e71b8f90bdc1e453fd1b9adbc5e6163898fb574543cb5be8.Terraform19196",
  "image": "https://ipfs.blockfrost.dev/ipfs/QmUdJ7LCBo1SJZTLFqPt8G1DWqMSfuVxBJ4j4Azszua4c4",
  "alpha_sector": "Asama",
  "activity": "Geothermal_Activity",
  "atmosphere": "Antigravity_Cloud",
  "bunker": "None",
  "fauna": "Livestock",
  "forests": "None",
  "hazardous_flora": "Melodious_Mantrap",
  "lithoglyphs": "Lithoglyphs_Purple",
  "power_level": 2,
  "quantum_flux": 6,
  "primary_minerals": "Copper",
  "secondary_minerals": "None",
  "ruins": "None",
  "shrine": "None",
  "water": "None",
  "location": {
    "x": 87,
    "y": 10
  }
}