{
  "token_name": "Terraform05542",
  "land_type": "Volcanic",
  "alpha_sector": "Arshi_En",
  "activity": "Geothermal_Activity",
  "atmosphere": "None",
  "bunker": "None",
  "fauna": "None",
  "forests": "Evergreen",
  "hazardous_flora": "Common_Hydra",
  "lithoglyphs": "Lithoglyphs_Green",
  "power_level": 1,
  "quantum_flux": 5,
  "primary_minerals": "None",
  "secondary_minerals": "Compacted_Machinery",
  "ruins": "None",
  "shrine": "None",
  "water": "Freshwater_River",
  "location": {
    "x": 47,
    "y": 42
  },
  "neighbors": {
    "top": {},
    "topRight": {},
    "right": {},
    "bottomRight": {},
    "bottom": {},
    "bottonLeft": {},
    "left": {},
    "topLeft": {}
  }
}