{
  "token_name": "Terraform14399",
  "land_type": "Volcanic",
  "pool_link": "https://pool.pm/c859e9d7e71b8f90bdc1e453fd1b9adbc5e6163898fb574543cb5be8.Terraform14399",
  "image": "https://ipfs.blockfrost.dev/ipfs/QmY2gSm9ma5xcCzfUULcyw44GDuA95KAXmF7zwc5hAk9Pz",
  "alpha_sector": "Arshi_En",
  "activity": "Geothermal_Activity",
  "atmosphere": "None",
  "bunker": "None",
  "fauna": "None",
  "forests": "None",
  "hazardous_flora": "Melodious_Mantrap",
  "lithoglyphs": "Lithoglyphs_Blue",
  "power_level": 2,
  "quantum_flux": 3,
  "primary_minerals": "Iron",
  "secondary_minerals": "None",
  "ruins": "None",
  "shrine": "None",
  "water": "None",
  "location": {
    "x": 19,
    "y": 84
  },
  "neighbors": {
    "top": {
      "x": 19,
      "y": 85
    },
    "topRight": {
      "x": 20,
      "y": 85
    },
    "right": {
      "x": 20,
      "y": 84
    },
    "bottomRight": {
      "x": 20,
      "y": 83
    },
    "bottom": {
      "x": 19,
      "y": 83
    },
    "bottonLeft": {
      "x": 18,
      "y": 83
    },
    "left": {
      "x": 18,
      "y": 84
    },
    "topLeft": {
      "x": 18,
      "y": 85
    }
  }
}