{
  "token_name": "Terraform06944",
  "land_type": "Fungal",
  "pool_link": "https://pool.pm/c859e9d7e71b8f90bdc1e453fd1b9adbc5e6163898fb574543cb5be8.Terraform06944",
  "image": "https://ipfs.blockfrost.dev/ipfs/QmV7ieaqbUhciDx1dNVBukR9mc8DNhEGv5LMgM4qUW4HNj",
  "alpha_sector": "Asama",
  "activity": "None",
  "atmosphere": "None",
  "bunker": "Reinforced_Bunker",
  "fauna": "Livestock",
  "forests": "None",
  "hazardous_flora": "Burning_Mantrap",
  "lithoglyphs": "None",
  "power_level": 7,
  "quantum_flux": 4,
  "primary_minerals": "Iron",
  "secondary_minerals": "None",
  "ruins": "None",
  "shrine": "None",
  "water": "None",
  "location": {
    "x": 42,
    "y": 16
  }
}