{
  "token_name": "Terraform01921",
  "land_type": "Wasteland",
  "alpha_sector": "Asama",
  "activity": "None",
  "atmosphere": "Custodial_Nanites",
  "bunker": "Quantum_Reinforced_Bunker",
  "fauna": "None",
  "forests": "None",
  "hazardous_flora": "None",
  "lithoglyphs": "None",
  "power_level": 5,
  "quantum_flux": 5,
  "primary_minerals": "Copper",
  "secondary_minerals": "Fossils",
  "ruins": "None",
  "shrine": "None",
  "water": "Saltwater_River",
  "location": {
    "x": 4,
    "y": 29
  },
  "neighbors": {
    "top": {},
    "topRight": {},
    "right": {},
    "bottomRight": {},
    "bottom": {},
    "bottonLeft": {},
    "left": {},
    "topLeft": {}
  }
}