{
  "token_name": "Terraform01881",
  "land_type": "Volcanic",
  "pool_link": "https://pool.pm/c859e9d7e71b8f90bdc1e453fd1b9adbc5e6163898fb574543cb5be8.Terraform01881",
  "image": "https://ipfs.blockfrost.dev/ipfs/QmaQjVD242YAoK6ohcNwWwEZzbV5cgHLhPw9xGAxVxoAMx",
  "alpha_sector": "Asama",
  "activity": "None",
  "atmosphere": "None",
  "bunker": "Reinforced_Bunker",
  "fauna": "None",
  "forests": "Evergreen",
  "hazardous_flora": "None",
  "lithoglyphs": "Lithoglyphs_Orange",
  "power_level": 3,
  "quantum_flux": 2,
  "primary_minerals": "None",
  "secondary_minerals": "Fossils",
  "ruins": "None",
  "shrine": "None",
  "water": "None",
  "location": {
    "x": 100,
    "y": 83
  },
  "neighbors": {
    "top": {
      "x": 100,
      "y": 84
    },
    "topRight": {
      "x": 101,
      "y": 84
    },
    "right": {
      "x": 101,
      "y": 83
    },
    "bottomRight": {
      "x": 101,
      "y": 82
    },
    "bottom": {
      "x": 100,
      "y": 82
    },
    "bottonLeft": {
      "x": 99,
      "y": 82
    },
    "left": {
      "x": 99,
      "y": 83
    },
    "topLeft": {
      "x": 99,
      "y": 84
    }
  }
}