{
  "token_name": "Terraform18261",
  "land_type": "Badlands",
  "pool_link": "https://pool.pm/c859e9d7e71b8f90bdc1e453fd1b9adbc5e6163898fb574543cb5be8.Terraform18261",
  "image": "https://ipfs.blockfrost.dev/ipfs/QmTQMBnJFaCkowDMYpGGTizVt223o9hAhrCi8BgPQekv5Z",
  "alpha_sector": "Asama",
  "activity": "None",
  "atmosphere": "Fungal_Spores",
  "bunker": "None",
  "fauna": "Ultrasaurs",
  "forests": "Palms",
  "hazardous_flora": "Common_Hydra",
  "lithoglyphs": "None",
  "power_level": 5,
  "quantum_flux": 5,
  "primary_minerals": "Copper",
  "secondary_minerals": "None",
  "ruins": "None",
  "shrine": "Machine_Shrine",
  "water": "Freshwater_River",
  "location": {
    "x": 6,
    "y": 33
  }
}