{
  "token_name": "Terraform15682",
  "land_type": "Grass",
  "alpha_sector": "Arshi_En",
  "activity": "None",
  "atmosphere": "Prismatic_Motes",
  "bunker": "None",
  "fauna": "None",
  "forests": "Evergreen",
  "hazardous_flora": "Burning_Mantrap",
  "lithoglyphs": "Lithoglyphs_Purple",
  "power_level": 6,
  "quantum_flux": 6,
  "primary_minerals": "Copper",
  "secondary_minerals": "None",
  "ruins": "None",
  "shrine": "None",
  "water": "None",
  "location": {
    "x": 26,
    "y": 95
  },
  "neighbors": {
    "top": {
      "token_name": "Terraform09540",
      "land_type": "Rocky",
      "alpha_sector": "Arshi_En",
      "activity": "None",
      "atmosphere": "None",
      "bunker": "None",
      "fauna": "None",
      "forests": "Prismaleaf",
      "hazardous_flora": "Burning_Mantrap",
      "lithoglyphs": "Lithoglyphs_Timelost",
      "power_level": 8,
      "quantum_flux": 6,
      "primary_minerals": "Copper",
      "secondary_minerals": "Compacted_Machinery",
      "ruins": "Ancient_Ruins",
      "shrine": "None",
      "water": "Cursed_Lake",
      "location": {
        "x": 26,
        "y": 96
      }
    },
    "topRight": {
      "token_name": "Terraform10693",
      "land_type": "Grass",
      "alpha_sector": "Arshi_En",
      "activity": "None",
      "atmosphere": "None",
      "bunker": "None",
      "fauna": "Livestock",
      "forests": "None",
      "hazardous_flora": "Common_Hydra",
      "lithoglyphs": "None",
      "power_level": 2,
      "quantum_flux": 3,
      "primary_minerals": "Iron",
      "secondary_minerals": "None",
      "ruins": "None",
      "shrine": "None",
      "water": "None",
      "location": {
        "x": 27,
        "y": 96
      }
    },
    "right": {
      "token_name": "Terraform05283",
      "land_type": "Rocky",
      "alpha_sector": "Arshi_En",
      "activity": "None",
      "atmosphere": "None",
      "bunker": "None",
      "fauna": "Critters",
      "forests": "None",
      "hazardous_flora": "Fungal_Hydra",
      "lithoglyphs": "Lithoglyphs_Red",
      "power_level": 1,
      "quantum_flux": 1,
      "primary_minerals": "Iron",
      "secondary_minerals": "None",
      "ruins": "None",
      "shrine": "Timelost_Shrine",
      "water": "Toxic_Lake",
      "location": {
        "x": 27,
        "y": 95
      }
    },
    "bottomRight": {
      "token_name": "Terraform08277",
      "land_type": "Rocky",
      "alpha_sector": "Arshi_En",
      "activity": "None",
      "atmosphere": "None",
      "bunker": "None",
      "fauna": "Critters",
      "forests": "Prismaleaf",
      "hazardous_flora": "None",
      "lithoglyphs": "Lithoglyphs_Orange",
      "power_level": 3,
      "quantum_flux": 6,
      "primary_minerals": "None",
      "secondary_minerals": "None",
      "ruins": "None",
      "shrine": "None",
      "water": "None",
      "location": {
        "x": 27,
        "y": 94
      }
    },
    "bottom": {
      "token_name": "Terraform01692",
      "land_type": "Grass",
      "alpha_sector": "Arshi_En",
      "activity": "None",
      "atmosphere": "None",
      "bunker": "Quantum_Reinforced_Bunker",
      "fauna": "Livestock",
      "forests": "Evergreen",
      "hazardous_flora": "Common_Hydra",
      "lithoglyphs": "Lithoglyphs_Purple",
      "power_level": 1,
      "quantum_flux": 1,
      "primary_minerals": "None",
      "secondary_minerals": "None",
      "ruins": "None",
      "shrine": "None",
      "water": "Freshwater_Lake",
      "location": {
        "x": 26,
        "y": 94
      }
    },
    "bottonLeft": {
      "token_name": "Terraform06576",
      "land_type": "Grass",
      "alpha_sector": "Arshi_En",
      "activity": "None",
      "atmosphere": "None",
      "bunker": "None",
      "fauna": "None",
      "forests": "None",
      "hazardous_flora": "None",
      "lithoglyphs": "Lithoglyphs_Timelost",
      "power_level": 5,
      "quantum_flux": 2,
      "primary_minerals": "Iron",
      "secondary_minerals": "None",
      "ruins": "None",
      "shrine": "Solar_Shrine",
      "water": "Funky_River",
      "location": {
        "x": 25,
        "y": 94
      }
    },
    "left": {
      "token_name": "Terraform00711",
      "land_type": "Fungal",
      "alpha_sector": "Arshi_En",
      "activity": "Geothermal_Activity",
      "atmosphere": "Prismatic_Motes",
      "bunker": "None",
      "fauna": "Livestock",
      "forests": "None",
      "hazardous_flora": "Giant_Mantrap",
      "lithoglyphs": "Lithoglyphs_Green",
      "power_level": 3,
      "quantum_flux": 8,
      "primary_minerals": "Iron",
      "secondary_minerals": "Compacted_Machinery",
      "ruins": "None",
      "shrine": "None",
      "water": "Cursed_River",
      "location": {
        "x": 25,
        "y": 95
      }
    },
    "topLeft": {
      "token_name": "Terraform18426",
      "land_type": "Tundra",
      "alpha_sector": "Arshi_En",
      "activity": "None",
      "atmosphere": "Antigravity_Cloud",
      "bunker": "None",
      "fauna": "None",
      "forests": "Evergreen",
      "hazardous_flora": "None",
      "lithoglyphs": "Lithoglyphs_Red",
      "power_level": 3,
      "quantum_flux": 7,
      "primary_minerals": "Iron",
      "secondary_minerals": "None",
      "ruins": "None",
      "shrine": "None",
      "water": "Saltwater_River",
      "location": {
        "x": 25,
        "y": 96
      }
    }
  }
}