{
  "token_name": "Terraform16277",
  "land_type": "Tundra",
  "pool_link": "https://pool.pm/c859e9d7e71b8f90bdc1e453fd1b9adbc5e6163898fb574543cb5be8.Terraform16277",
  "image": "https://ipfs.blockfrost.dev/ipfs/QmU7fmdVh5hKGRbxN9Nx4KPioKXHfd1zZJ1xTMLzKgoh1M",
  "alpha_sector": "Asama",
  "activity": "None",
  "atmosphere": "Fungal_Spores",
  "bunker": "None",
  "fauna": "None",
  "forests": "Evergreen",
  "hazardous_flora": "Common_Hydra",
  "lithoglyphs": "Lithoglyphs_Timelost",
  "power_level": 6,
  "quantum_flux": 6,
  "primary_minerals": "Iron",
  "secondary_minerals": "None",
  "ruins": "Alien_Technology_Blue",
  "shrine": "None",
  "water": "None",
  "location": {
    "x": 72,
    "y": 32
  }
}