{
  "token_name": "Terraform17780",
  "land_type": "Artificial",
  "alpha_sector": "Arshi_En",
  "activity": "None",
  "atmosphere": "Custodial_Nanites",
  "bunker": "None",
  "fauna": "None",
  "forests": "Evergreen",
  "hazardous_flora": "Burning_Mantrap",
  "lithoglyphs": "None",
  "power_level": 2,
  "quantum_flux": 2,
  "primary_minerals": "None",
  "secondary_minerals": "Fossils",
  "ruins": "None",
  "shrine": "None",
  "water": "Freshwater_Lake",
  "location": {
    "x": 19,
    "y": 100
  },
  "neighbors": {
    "top": {},
    "topRight": {},
    "right": {
      "token_name": "Terraform00518",
      "land_type": "Tundra",
      "alpha_sector": "Arshi_En",
      "activity": "None",
      "atmosphere": "None",
      "bunker": "None",
      "fauna": "Livestock",
      "forests": "Evergreen",
      "hazardous_flora": "Common_Hydra",
      "lithoglyphs": "None",
      "power_level": 2,
      "quantum_flux": 9,
      "primary_minerals": "Iron",
      "secondary_minerals": "None",
      "ruins": "Alien_Technology_Purple",
      "shrine": "None",
      "water": "None",
      "location": {
        "x": 20,
        "y": 100
      }
    },
    "bottomRight": {
      "token_name": "Terraform15032",
      "land_type": "Fungal",
      "alpha_sector": "Arshi_En",
      "activity": "None",
      "atmosphere": "Prismatic_Motes",
      "bunker": "None",
      "fauna": "Livestock",
      "forests": "Prismaleaf",
      "hazardous_flora": "Fungal_Hydra",
      "lithoglyphs": "Lithoglyphs_Timelost",
      "power_level": 1,
      "quantum_flux": 6,
      "primary_minerals": "Iron",
      "secondary_minerals": "None",
      "ruins": "Alien_Technology_Orange",
      "shrine": "Void_Shrine",
      "water": "None",
      "location": {
        "x": 20,
        "y": 99
      }
    },
    "bottom": {
      "token_name": "Terraform07148",
      "land_type": "Grass",
      "alpha_sector": "Arshi_En",
      "activity": "Geothermal_Activity",
      "atmosphere": "Fungal_Spores",
      "bunker": "Cardanium_Bunker",
      "fauna": "Ultrasaurs",
      "forests": "Palms",
      "hazardous_flora": "Common_Hydra",
      "lithoglyphs": "Lithoglyphs_Blue",
      "power_level": 8,
      "quantum_flux": 6,
      "primary_minerals": "Copper",
      "secondary_minerals": "Fossils",
      "ruins": "None",
      "shrine": "None",
      "water": "None",
      "location": {
        "x": 19,
        "y": 99
      }
    },
    "bottonLeft": {
      "token_name": "Terraform08686",
      "land_type": "Desert",
      "alpha_sector": "Arshi_En",
      "activity": "None",
      "atmosphere": "None",
      "bunker": "Quantum_Reinforced_Bunker",
      "fauna": "None",
      "forests": "None",
      "hazardous_flora": "Fungal_Hydra",
      "lithoglyphs": "None",
      "power_level": 7,
      "quantum_flux": 3,
      "primary_minerals": "Radium",
      "secondary_minerals": "Gemstones",
      "ruins": "Alien_Technology_Green",
      "shrine": "Solar_Shrine",
      "water": "Freshwater_River",
      "location": {
        "x": 18,
        "y": 99
      }
    },
    "left": {
      "token_name": "Terraform01903",
      "land_type": "Rocky",
      "alpha_sector": "Arshi_En",
      "activity": "None",
      "atmosphere": "Fungal_Spores",
      "bunker": "Quantum_Reinforced_Bunker",
      "fauna": "Critters",
      "forests": "Evergreen",
      "hazardous_flora": "Burning_Mantrap",
      "lithoglyphs": "Lithoglyphs_Purple",
      "power_level": 4,
      "quantum_flux": 3,
      "primary_minerals": "None",
      "secondary_minerals": "None",
      "ruins": "None",
      "shrine": "Void_Shrine",
      "water": "Freshwater_Lake",
      "location": {
        "x": 18,
        "y": 100
      }
    },
    "topLeft": {}
  }
}