{
  "token_name": "Terraform12238",
  "land_type": "Grass",
  "alpha_sector": "Asama",
  "activity": "Geothermal_Activity",
  "atmosphere": "Custodial_Nanites",
  "bunker": "Reinforced_Bunker",
  "fauna": "Livestock",
  "forests": "None",
  "hazardous_flora": "Giant_Mantrap",
  "lithoglyphs": "Lithoglyphs_Green",
  "power_level": 1,
  "quantum_flux": 6,
  "primary_minerals": "None",
  "secondary_minerals": "Fossils",
  "ruins": "Alien_Technology_Green",
  "shrine": "None",
  "water": "None",
  "location": {
    "x": 100,
    "y": 12
  },
  "neighbors": {
    "top": {},
    "topRight": {},
    "right": {},
    "bottomRight": {},
    "bottom": {},
    "bottonLeft": {},
    "left": {},
    "topLeft": {}
  }
}