{
  "token_name": "Terraform04630",
  "land_type": "Wasteland",
  "pool_link": "https://pool.pm/c859e9d7e71b8f90bdc1e453fd1b9adbc5e6163898fb574543cb5be8.Terraform04630",
  "image": "https://ipfs.blockfrost.dev/ipfs/QmUUCiwPJVY4BeFqraaWUyVAsLRLrQBWxCigddSQii8MoC",
  "alpha_sector": "Asama",
  "activity": "Magnetic_Activity",
  "atmosphere": "None",
  "bunker": "None",
  "fauna": "Critters",
  "forests": "None",
  "hazardous_flora": "Giant_Mantrap",
  "lithoglyphs": "Lithoglyphs_Blue",
  "power_level": 5,
  "quantum_flux": 1,
  "primary_minerals": "Radium",
  "secondary_minerals": "None",
  "ruins": "None",
  "shrine": "None",
  "water": "Freshwater_River",
  "location": {
    "x": 36,
    "y": 33
  }
}