{
  "token_name": "Terraform06632",
  "land_type": "Desert",
  "pool_link": "https://pool.pm/c859e9d7e71b8f90bdc1e453fd1b9adbc5e6163898fb574543cb5be8.Terraform06632",
  "image": "https://ipfs.blockfrost.dev/ipfs/QmUkYWR9SRcj7emuXtGQbo2ECawygtwYbHwSjC2ut1rA9E",
  "alpha_sector": "Arshi_En",
  "activity": "None",
  "atmosphere": "None",
  "bunker": "Reinforced_Bunker",
  "fauna": "Livestock",
  "forests": "None",
  "hazardous_flora": "Melodious_Mantrap",
  "lithoglyphs": "Lithoglyphs_Timelost",
  "power_level": 4,
  "quantum_flux": 4,
  "primary_minerals": "None",
  "secondary_minerals": "None",
  "ruins": "None",
  "shrine": "Quantum_Shrine",
  "water": "Freshwater_Lake",
  "location": {
    "x": 100,
    "y": 77
  }
}