{
  "token_name": "Terraform17877",
  "land_type": "Desert",
  "alpha_sector": "Arshi_En",
  "activity": "Magnetic_Activity",
  "atmosphere": "Fungal_Spores",
  "bunker": "None",
  "fauna": "None",
  "forests": "None",
  "hazardous_flora": "None",
  "lithoglyphs": "Lithoglyphs_Red",
  "power_level": 9,
  "quantum_flux": 8,
  "primary_minerals": "Iron",
  "secondary_minerals": "None",
  "ruins": "Alien_Technology_Blue",
  "shrine": "None",
  "water": "None",
  "location": {
    "x": 68,
    "y": 25
  },
  "neighbors": {
    "top": {},
    "topRight": {},
    "right": {},
    "bottomRight": {},
    "bottom": {},
    "bottonLeft": {},
    "left": {},
    "topLeft": {}
  }
}