{
  "token_name": "Terraform10439",
  "land_type": "Grass",
  "pool_link": "https://pool.pm/c859e9d7e71b8f90bdc1e453fd1b9adbc5e6163898fb574543cb5be8.Terraform10439",
  "image": "https://ipfs.blockfrost.dev/ipfs/Qma5iU7CQ2kwPf3sT2DFpcehQwWt63ELWEy4Y9fQBPE4Yb",
  "alpha_sector": "Arshi_En",
  "activity": "None",
  "atmosphere": "Cursed_Nanites",
  "bunker": "Quantum_Reinforced_Bunker",
  "fauna": "None",
  "forests": "Palms",
  "hazardous_flora": "None",
  "lithoglyphs": "Lithoglyphs_Red",
  "power_level": 7,
  "quantum_flux": 3,
  "primary_minerals": "Copper",
  "secondary_minerals": "None",
  "ruins": "None",
  "shrine": "Solar_Shrine",
  "water": "None",
  "location": {
    "x": 80,
    "y": 89
  }
}