{
  "token_name": "Terraform03535",
  "land_type": "Grass",
  "pool_link": "https://pool.pm/c859e9d7e71b8f90bdc1e453fd1b9adbc5e6163898fb574543cb5be8.Terraform03535",
  "image": "https://ipfs.blockfrost.dev/ipfs/QmedsVs6YxS7MVM4afs5iFG4CrYX6pnDsRj2DxXf8LAimZ",
  "alpha_sector": "Arshi_En",
  "activity": "None",
  "atmosphere": "Cursed_Nanites",
  "bunker": "Reinforced_Bunker",
  "fauna": "Critters",
  "forests": "Prismaleaf",
  "hazardous_flora": "Giant_Mantrap",
  "lithoglyphs": "None",
  "power_level": 5,
  "quantum_flux": 3,
  "primary_minerals": "Iron",
  "secondary_minerals": "None",
  "ruins": "Ancient_Ruins",
  "shrine": "None",
  "water": "Cursed_River",
  "location": {
    "x": 55,
    "y": 72
  }
}