{
  "token_name": "Terraform06596",
  "land_type": "Grass",
  "alpha_sector": "Arshi_En",
  "activity": "Magnetic_Activity",
  "atmosphere": "None",
  "bunker": "None",
  "fauna": "None",
  "forests": "None",
  "hazardous_flora": "Burning_Mantrap",
  "lithoglyphs": "None",
  "power_level": 1,
  "quantum_flux": 8,
  "primary_minerals": "Copper",
  "secondary_minerals": "Gemstones",
  "ruins": "None",
  "shrine": "None",
  "water": "None",
  "location": {
    "x": 53,
    "y": 49
  },
  "neighbors": {
    "top": {
      "token_name": "Terraform15085",
      "land_type": "Tundra",
      "alpha_sector": "Arshi_En",
      "activity": "None",
      "atmosphere": "Antigravity_Cloud",
      "bunker": "None",
      "fauna": "None",
      "forests": "Palms",
      "hazardous_flora": "None",
      "lithoglyphs": "Lithoglyphs_Blue",
      "power_level": 2,
      "quantum_flux": 6,
      "primary_minerals": "None",
      "secondary_minerals": "None",
      "ruins": "Alien_Technology_Orange",
      "shrine": "None",
      "water": "Freshwater_River",
      "location": {
        "x": 53,
        "y": 50
      }
    },
    "topRight": {
      "token_name": "Terraform04724",
      "land_type": "Badlands",
      "alpha_sector": "Arshi_En",
      "activity": "None",
      "atmosphere": "None",
      "bunker": "Reinforced_Bunker",
      "fauna": "Ultrasaurs",
      "forests": "None",
      "hazardous_flora": "Common_Hydra",
      "lithoglyphs": "None",
      "power_level": 9,
      "quantum_flux": 7,
      "primary_minerals": "Iron",
      "secondary_minerals": "None",
      "ruins": "None",
      "shrine": "None",
      "water": "None",
      "location": {
        "x": 54,
        "y": 50
      }
    },
    "right": {
      "token_name": "Terraform04933",
      "land_type": "Wasteland",
      "alpha_sector": "Arshi_En",
      "activity": "Magnetic_Activity",
      "atmosphere": "None",
      "bunker": "Reinforced_Bunker",
      "fauna": "None",
      "forests": "Palms",
      "hazardous_flora": "Fungal_Hydra",
      "lithoglyphs": "Lithoglyphs_Green",
      "power_level": 2,
      "quantum_flux": 3,
      "primary_minerals": "Iron",
      "secondary_minerals": "None",
      "ruins": "None",
      "shrine": "Timelost_Shrine",
      "water": "None",
      "location": {
        "x": 54,
        "y": 49
      }
    },
    "bottomRight": {
      "token_name": "Terraform18633",
      "land_type": "Grass",
      "alpha_sector": "Arshi_En",
      "activity": "Magnetic_Activity",
      "atmosphere": "None",
      "bunker": "Quantum_Reinforced_Bunker",
      "fauna": "None",
      "forests": "None",
      "hazardous_flora": "None",
      "lithoglyphs": "Lithoglyphs_Green",
      "power_level": 2,
      "quantum_flux": 1,
      "primary_minerals": "Iron",
      "secondary_minerals": "None",
      "ruins": "Alien_Technology_Green",
      "shrine": "None",
      "water": "None",
      "location": {
        "x": 54,
        "y": 48
      }
    },
    "bottom": {
      "token_name": "Terraform02371",
      "land_type": "Wasteland",
      "alpha_sector": "Arshi_En",
      "activity": "None",
      "atmosphere": "None",
      "bunker": "Reinforced_Bunker",
      "fauna": "Critters",
      "forests": "Prismaleaf",
      "hazardous_flora": "Common_Hydra",
      "lithoglyphs": "Lithoglyphs_Green",
      "power_level": 1,
      "quantum_flux": 1,
      "primary_minerals": "None",
      "secondary_minerals": "None",
      "ruins": "None",
      "shrine": "None",
      "water": "Freshwater_River",
      "location": {
        "x": 53,
        "y": 48
      }
    },
    "bottonLeft": {
      "token_name": "Terraform01730",
      "land_type": "Tundra",
      "alpha_sector": "Arshi_En",
      "activity": "None",
      "atmosphere": "None",
      "bunker": "Cardanium_Bunker",
      "fauna": "Ultrasaurs",
      "forests": "Evergreen",
      "hazardous_flora": "None",
      "lithoglyphs": "Lithoglyphs_Blue",
      "power_level": 1,
      "quantum_flux": 2,
      "primary_minerals": "Cardanium",
      "secondary_minerals": "None",
      "ruins": "None",
      "shrine": "None",
      "water": "Freshwater_Lake",
      "location": {
        "x": 52,
        "y": 48
      }
    },
    "left": {
      "token_name": "Terraform13787",
      "land_type": "Volcanic",
      "alpha_sector": "Arshi_En",
      "activity": "None",
      "atmosphere": "None",
      "bunker": "None",
      "fauna": "Critters",
      "forests": "None",
      "hazardous_flora": "None",
      "lithoglyphs": "Lithoglyphs_Purple",
      "power_level": 6,
      "quantum_flux": 6,
      "primary_minerals": "None",
      "secondary_minerals": "Gemstones",
      "ruins": "None",
      "shrine": "None",
      "water": "None",
      "location": {
        "x": 52,
        "y": 49
      }
    },
    "topLeft": {
      "token_name": "Terraform12306",
      "land_type": "Tundra",
      "alpha_sector": "Arshi_En",
      "activity": "None",
      "atmosphere": "Prismatic_Motes",
      "bunker": "Reinforced_Bunker",
      "fauna": "Ultrasaurs",
      "forests": "None",
      "hazardous_flora": "Common_Hydra",
      "lithoglyphs": "Lithoglyphs_Green",
      "power_level": 2,
      "quantum_flux": 1,
      "primary_minerals": "Copper",
      "secondary_minerals": "Fossils",
      "ruins": "None",
      "shrine": "Void_Shrine",
      "water": "Cursed_Lake",
      "location": {
        "x": 52,
        "y": 50
      }
    }
  }
}