{
  "token_name": "Terraform01868",
  "land_type": "Grass",
  "pool_link": "https://pool.pm/c859e9d7e71b8f90bdc1e453fd1b9adbc5e6163898fb574543cb5be8.Terraform01868",
  "image": "https://ipfs.blockfrost.dev/ipfs/Qmb5Qu5cJcWtwbTCMTKN9xsgWBFE3rBEvo93itzL1vRKL2",
  "alpha_sector": "Arshi_En",
  "activity": "None",
  "atmosphere": "None",
  "bunker": "None",
  "fauna": "None",
  "forests": "None",
  "hazardous_flora": "Burning_Mantrap",
  "lithoglyphs": "None",
  "power_level": 7,
  "quantum_flux": 2,
  "primary_minerals": "None",
  "secondary_minerals": "None",
  "ruins": "None",
  "shrine": "Machine_Shrine",
  "water": "None",
  "location": {
    "x": 62,
    "y": 20
  },
  "neighbors": {
    "top": {
      "x": 62,
      "y": 21
    },
    "topRight": {
      "x": 63,
      "y": 21
    },
    "right": {
      "x": 63,
      "y": 20
    },
    "bottomRight": {
      "x": 63,
      "y": 19
    },
    "bottom": {
      "x": 62,
      "y": 19
    },
    "bottonLeft": {
      "x": 61,
      "y": 19
    },
    "left": {
      "x": 61,
      "y": 20
    },
    "topLeft": {
      "x": 61,
      "y": 21
    }
  }
}