{
  "token_name": "Terraform09839",
  "land_type": "Rocky",
  "alpha_sector": "Asama",
  "activity": "None",
  "atmosphere": "None",
  "bunker": "None",
  "fauna": "Critters",
  "forests": "Prismaleaf",
  "hazardous_flora": "Melodious_Mantrap",
  "lithoglyphs": "None",
  "power_level": 1,
  "quantum_flux": 7,
  "primary_minerals": "None",
  "secondary_minerals": "Gemstones",
  "ruins": "Alien_Technology_Blue",
  "shrine": "None",
  "water": "Cursed_River",
  "location": {
    "x": 55,
    "y": 51
  },
  "neighbors": {
    "top": {},
    "topRight": {},
    "right": {},
    "bottomRight": {},
    "bottom": {},
    "bottonLeft": {},
    "left": {},
    "topLeft": {}
  }
}