{
  "token_name": "Terraform09900",
  "land_type": "Grass",
  "alpha_sector": "Arshi_En",
  "activity": "None",
  "atmosphere": "Fungal_Spores",
  "bunker": "None",
  "fauna": "Livestock",
  "forests": "None",
  "hazardous_flora": "Burning_Mantrap",
  "lithoglyphs": "Lithoglyphs_Blue",
  "power_level": 1,
  "quantum_flux": 2,
  "primary_minerals": "None",
  "secondary_minerals": "None",
  "ruins": "None",
  "shrine": "None",
  "water": "Freshwater_River",
  "location": {
    "x": 68,
    "y": 93
  },
  "neighbors": {
    "top": {
      "token_name": "Terraform11087",
      "land_type": "Rocky",
      "alpha_sector": "Arshi_En",
      "activity": "None",
      "atmosphere": "None",
      "bunker": "Cardanium_Bunker",
      "fauna": "Critters",
      "forests": "Palms",
      "hazardous_flora": "Burning_Mantrap",
      "lithoglyphs": "Lithoglyphs_Green",
      "power_level": 7,
      "quantum_flux": 1,
      "primary_minerals": "None",
      "secondary_minerals": "None",
      "ruins": "Alien_Technology_Orange",
      "shrine": "None",
      "water": "Freshwater_River",
      "location": {
        "x": 68,
        "y": 94
      }
    },
    "topRight": {
      "token_name": "Terraform17471",
      "land_type": "Grass",
      "alpha_sector": "Arshi_En",
      "activity": "None",
      "atmosphere": "None",
      "bunker": "Reinforced_Bunker",
      "fauna": "None",
      "forests": "None",
      "hazardous_flora": "None",
      "lithoglyphs": "Lithoglyphs_Timelost",
      "power_level": 2,
      "quantum_flux": 1,
      "primary_minerals": "None",
      "secondary_minerals": "None",
      "ruins": "None",
      "shrine": "Machine_Shrine",
      "water": "None",
      "location": {
        "x": 69,
        "y": 94
      }
    },
    "right": {
      "token_name": "Terraform00922",
      "land_type": "Volcanic",
      "alpha_sector": "Arshi_En",
      "activity": "None",
      "atmosphere": "None",
      "bunker": "None",
      "fauna": "None",
      "forests": "Palms",
      "hazardous_flora": "Common_Hydra",
      "lithoglyphs": "None",
      "power_level": 2,
      "quantum_flux": 1,
      "primary_minerals": "None",
      "secondary_minerals": "None",
      "ruins": "None",
      "shrine": "None",
      "water": "None",
      "location": {
        "x": 69,
        "y": 93
      }
    },
    "bottomRight": {
      "token_name": "Terraform07053",
      "land_type": "Grass",
      "alpha_sector": "Arshi_En",
      "activity": "None",
      "atmosphere": "None",
      "bunker": "None",
      "fauna": "Critters",
      "forests": "Prismaleaf",
      "hazardous_flora": "Common_Hydra",
      "lithoglyphs": "None",
      "power_level": 4,
      "quantum_flux": 3,
      "primary_minerals": "Iron",
      "secondary_minerals": "Fossils",
      "ruins": "None",
      "shrine": "None",
      "water": "None",
      "location": {
        "x": 69,
        "y": 92
      }
    },
    "bottom": {
      "token_name": "Terraform11475",
      "land_type": "Wasteland",
      "alpha_sector": "Arshi_En",
      "activity": "None",
      "atmosphere": "None",
      "bunker": "None",
      "fauna": "Livestock",
      "forests": "Evergreen",
      "hazardous_flora": "None",
      "lithoglyphs": "Lithoglyphs_Purple",
      "power_level": 6,
      "quantum_flux": 3,
      "primary_minerals": "None",
      "secondary_minerals": "None",
      "ruins": "None",
      "shrine": "None",
      "water": "None",
      "location": {
        "x": 68,
        "y": 92
      }
    },
    "bottonLeft": {
      "token_name": "Terraform17283",
      "land_type": "Volcanic",
      "alpha_sector": "Arshi_En",
      "activity": "None",
      "atmosphere": "None",
      "bunker": "None",
      "fauna": "Livestock",
      "forests": "Evergreen",
      "hazardous_flora": "Giant_Mantrap",
      "lithoglyphs": "None",
      "power_level": 1,
      "quantum_flux": 1,
      "primary_minerals": "Cardanium",
      "secondary_minerals": "None",
      "ruins": "None",
      "shrine": "None",
      "water": "Freshwater_River",
      "location": {
        "x": 67,
        "y": 92
      }
    },
    "left": {
      "token_name": "Terraform08857",
      "land_type": "Rocky",
      "alpha_sector": "Arshi_En",
      "activity": "None",
      "atmosphere": "None",
      "bunker": "Quantum_Reinforced_Bunker",
      "fauna": "None",
      "forests": "None",
      "hazardous_flora": "Giant_Mantrap",
      "lithoglyphs": "Lithoglyphs_Red",
      "power_level": 6,
      "quantum_flux": 7,
      "primary_minerals": "None",
      "secondary_minerals": "Gemstones",
      "ruins": "None",
      "shrine": "None",
      "water": "Freshwater_River",
      "location": {
        "x": 67,
        "y": 93
      }
    },
    "topLeft": {
      "token_name": "Terraform12984",
      "land_type": "Grass",
      "alpha_sector": "Arshi_En",
      "activity": "None",
      "atmosphere": "None",
      "bunker": "None",
      "fauna": "Ultrasaurs",
      "forests": "None",
      "hazardous_flora": "Fungal_Hydra",
      "lithoglyphs": "None",
      "power_level": 3,
      "quantum_flux": 2,
      "primary_minerals": "Copper",
      "secondary_minerals": "None",
      "ruins": "None",
      "shrine": "None",
      "water": "Toxic_Lake",
      "location": {
        "x": 67,
        "y": 94
      }
    }
  }
}