{
  "token_name": "Terraform00301",
  "land_type": "Tundra",
  "pool_link": "https://pool.pm/c859e9d7e71b8f90bdc1e453fd1b9adbc5e6163898fb574543cb5be8.Terraform00301",
  "image": "https://ipfs.blockfrost.dev/ipfs/QmUbVmbuyzPieDCeYmMwNCG6NErkzuwFQ6FUFATMUhVwpp",
  "alpha_sector": "Arshi_En",
  "activity": "Magnetic_Activity",
  "atmosphere": "None",
  "bunker": "None",
  "fauna": "Livestock",
  "forests": "None",
  "hazardous_flora": "Fungal_Hydra",
  "lithoglyphs": "None",
  "power_level": 6,
  "quantum_flux": 8,
  "primary_minerals": "None",
  "secondary_minerals": "Fossils",
  "ruins": "None",
  "shrine": "None",
  "water": "Funky_River",
  "location": {
    "x": 94,
    "y": 8
  },
  "neighbors": {
    "top": {
      "x": 94,
      "y": 9
    },
    "topRight": {
      "x": 95,
      "y": 9
    },
    "right": {
      "x": 95,
      "y": 8
    },
    "bottomRight": {
      "x": 95,
      "y": 7
    },
    "bottom": {
      "x": 94,
      "y": 7
    },
    "bottonLeft": {
      "x": 93,
      "y": 7
    },
    "left": {
      "x": 93,
      "y": 8
    },
    "topLeft": {
      "x": 93,
      "y": 9
    }
  }
}