{
  "token_name": "Terraform13514",
  "land_type": "Grass",
  "pool_link": "https://pool.pm/c859e9d7e71b8f90bdc1e453fd1b9adbc5e6163898fb574543cb5be8.Terraform13514",
  "image": "https://ipfs.blockfrost.dev/ipfs/QmcbQV4tcigNh5g13Szt9VE4UwMQ1gAjEzAka4vzEZHSUx",
  "alpha_sector": "Asama",
  "activity": "None",
  "atmosphere": "Custodial_Nanites",
  "bunker": "None",
  "fauna": "None",
  "forests": "None",
  "hazardous_flora": "None",
  "lithoglyphs": "Lithoglyphs_Orange",
  "power_level": 4,
  "quantum_flux": 6,
  "primary_minerals": "None",
  "secondary_minerals": "None",
  "ruins": "None",
  "shrine": "None",
  "water": "Saltwater_River",
  "location": {
    "x": 87,
    "y": 26
  }
}