{
  "token_name": "Terraform00743",
  "land_type": "Rocky",
  "pool_link": "https://pool.pm/c859e9d7e71b8f90bdc1e453fd1b9adbc5e6163898fb574543cb5be8.Terraform00743",
  "image": "https://ipfs.blockfrost.dev/ipfs/QmTxvH5jo4z4UDdxGh8sQJG2Cbjk9PD76VgzK7oyEdtvAE",
  "alpha_sector": "Asama",
  "activity": "None",
  "atmosphere": "Fungal_Spores",
  "bunker": "None",
  "fauna": "Livestock",
  "forests": "None",
  "hazardous_flora": "Giant_Mantrap",
  "lithoglyphs": "Lithoglyphs_Blue",
  "power_level": 6,
  "quantum_flux": 4,
  "primary_minerals": "Cardanium",
  "secondary_minerals": "None",
  "ruins": "None",
  "shrine": "None",
  "water": "None",
  "location": {
    "x": 28,
    "y": 45
  }
}