{
  "token_name": "Terraform13515",
  "land_type": "Rocky",
  "alpha_sector": "Asama",
  "activity": "Magnetic_Activity",
  "atmosphere": "Fungal_Spores",
  "bunker": "None",
  "fauna": "None",
  "forests": "Palms",
  "hazardous_flora": "None",
  "lithoglyphs": "Lithoglyphs_Purple",
  "power_level": 5,
  "quantum_flux": 3,
  "primary_minerals": "Copper",
  "secondary_minerals": "Fossils",
  "ruins": "None",
  "shrine": "Machine_Shrine",
  "water": "Freshwater_Lake",
  "location": {
    "x": 72,
    "y": 50
  },
  "neighbors": {
    "top": {},
    "topRight": {},
    "right": {},
    "bottomRight": {},
    "bottom": {},
    "bottonLeft": {},
    "left": {},
    "topLeft": {}
  }
}