{
  "token_name": "Terraform19421",
  "land_type": "Tundra",
  "alpha_sector": "Arshi_En",
  "activity": "Geothermal_Activity",
  "atmosphere": "Custodial_Nanites",
  "bunker": "Cardanium_Bunker",
  "fauna": "None",
  "forests": "None",
  "hazardous_flora": "Common_Hydra",
  "lithoglyphs": "Lithoglyphs_Green",
  "power_level": 6,
  "quantum_flux": 5,
  "primary_minerals": "Copper",
  "secondary_minerals": "None",
  "ruins": "Alien_Technology_Red",
  "shrine": "None",
  "water": "Freshwater_River",
  "location": {
    "x": 60,
    "y": 50
  },
  "neighbors": {
    "top": {},
    "topRight": {},
    "right": {},
    "bottomRight": {},
    "bottom": {},
    "bottonLeft": {},
    "left": {},
    "topLeft": {}
  }
}