{
  "token_name": "Terraform17739",
  "land_type": "Fungal",
  "pool_link": "https://pool.pm/c859e9d7e71b8f90bdc1e453fd1b9adbc5e6163898fb574543cb5be8.Terraform17739",
  "image": "https://ipfs.blockfrost.dev/ipfs/Qmd4JhL2UAxrgp46V26JXgx5zmqQ1QUBKaYY4XDD6KYkEi",
  "alpha_sector": "Arshi_En",
  "activity": "None",
  "atmosphere": "None",
  "bunker": "None",
  "fauna": "Ultrasaurs",
  "forests": "Evergreen",
  "hazardous_flora": "Burning_Mantrap",
  "lithoglyphs": "Lithoglyphs_Orange",
  "power_level": 4,
  "quantum_flux": 2,
  "primary_minerals": "None",
  "secondary_minerals": "None",
  "ruins": "Alien_Technology_Purple",
  "shrine": "None",
  "water": "None",
  "location": {
    "x": 74,
    "y": 40
  }
}