{
  "token_name": "Terraform01643",
  "land_type": "Grass",
  "pool_link": "https://pool.pm/c859e9d7e71b8f90bdc1e453fd1b9adbc5e6163898fb574543cb5be8.Terraform01643",
  "image": "https://ipfs.blockfrost.dev/ipfs/QmcmgsYsNpAZtV12hjrMkH9pjLP9NLFZZCTCXeCBPpERmr",
  "alpha_sector": "Asama",
  "activity": "None",
  "atmosphere": "None",
  "bunker": "Reinforced_Bunker",
  "fauna": "None",
  "forests": "None",
  "hazardous_flora": "Common_Hydra",
  "lithoglyphs": "None",
  "power_level": 1,
  "quantum_flux": 8,
  "primary_minerals": "None",
  "secondary_minerals": "None",
  "ruins": "Alien_Technology_Timelost",
  "shrine": "None",
  "water": "None",
  "location": {
    "x": 60,
    "y": 34
  }
}