{
  "token_name": "Terraform00897",
  "land_type": "Rocky",
  "pool_link": "https://pool.pm/c859e9d7e71b8f90bdc1e453fd1b9adbc5e6163898fb574543cb5be8.Terraform00897",
  "image": "https://ipfs.blockfrost.dev/ipfs/QmUyrXSkJ578NECm7HuuE7FfiqxcPyLGZEE6iDGSKiK7B2",
  "alpha_sector": "Arshi_En",
  "activity": "Geothermal_Activity",
  "atmosphere": "Cursed_Nanites",
  "bunker": "None",
  "fauna": "Livestock",
  "forests": "None",
  "hazardous_flora": "Giant_Mantrap",
  "lithoglyphs": "Lithoglyphs_Purple",
  "power_level": 9,
  "quantum_flux": 5,
  "primary_minerals": "Iron",
  "secondary_minerals": "None",
  "ruins": "Alien_Technology_Green",
  "shrine": "None",
  "water": "Saltwater_River",
  "location": {
    "x": 50,
    "y": 32
  }
}