{
  "token_name": "Terraform19887",
  "land_type": "Prismatic",
  "pool_link": "https://pool.pm/c859e9d7e71b8f90bdc1e453fd1b9adbc5e6163898fb574543cb5be8.Terraform19887",
  "image": "https://ipfs.blockfrost.dev/ipfs/QmVjRacm5LM48U6yURs3qfVJQaH2Jbs6BhVuFiiqea7K4k",
  "alpha_sector": "Foundation",
  "activity": "None",
  "atmosphere": "None",
  "bunker": "None",
  "fauna": "Ultrasaurs",
  "forests": "None",
  "hazardous_flora": "Common_Hydra",
  "lithoglyphs": "None",
  "power_level": 5,
  "quantum_flux": 7,
  "primary_minerals": "Iron",
  "secondary_minerals": "None",
  "ruins": "None",
  "shrine": "None",
  "water": "Freshwater_Lake",
  "location": {
    "x": 15,
    "y": 4
  }
}