{
  "token_name": "Terraform10956",
  "land_type": "Grass",
  "pool_link": "https://pool.pm/c859e9d7e71b8f90bdc1e453fd1b9adbc5e6163898fb574543cb5be8.Terraform10956",
  "image": "https://ipfs.blockfrost.dev/ipfs/QmZCPxJnUGgKMqBBN6zw96sN6yQ5KcFBkDKzKyAvqTx8S1",
  "alpha_sector": "Asama",
  "activity": "Geothermal_Activity",
  "atmosphere": "Fungal_Spores",
  "bunker": "None",
  "fauna": "None",
  "forests": "Evergreen",
  "hazardous_flora": "None",
  "lithoglyphs": "Lithoglyphs_Blue",
  "power_level": 7,
  "quantum_flux": 4,
  "primary_minerals": "Cardanium",
  "secondary_minerals": "Compacted_Machinery",
  "ruins": "None",
  "shrine": "None",
  "water": "None",
  "location": {
    "x": 3,
    "y": 46
  }
}