{
  "token_name": "Terraform18131",
  "land_type": "Grass",
  "pool_link": "https://pool.pm/c859e9d7e71b8f90bdc1e453fd1b9adbc5e6163898fb574543cb5be8.Terraform18131",
  "image": "https://ipfs.blockfrost.dev/ipfs/Qmf6CFvc86rKgraJpD4a99RkXyxQMkFwbWj8tYCf1goYB8",
  "alpha_sector": "Arshi_En",
  "activity": "None",
  "atmosphere": "Prismatic_Motes",
  "bunker": "None",
  "fauna": "Ultrasaurs",
  "forests": "None",
  "hazardous_flora": "Fungal_Hydra",
  "lithoglyphs": "None",
  "power_level": 2,
  "quantum_flux": 8,
  "primary_minerals": "Iron",
  "secondary_minerals": "None",
  "ruins": "None",
  "shrine": "None",
  "water": "Freshwater_River",
  "location": {
    "x": 98,
    "y": 43
  }
}