{
  "token_name": "Terraform10385",
  "land_type": "Rocky",
  "pool_link": "https://pool.pm/c859e9d7e71b8f90bdc1e453fd1b9adbc5e6163898fb574543cb5be8.Terraform10385",
  "image": "https://ipfs.blockfrost.dev/ipfs/Qmf1cdV1Lxb6mV4UJoa2yMWmK4SUpS5gWsZMRNwaLhcTxx",
  "alpha_sector": "Arshi_En",
  "activity": "Magnetic_Activity",
  "atmosphere": "None",
  "bunker": "None",
  "fauna": "None",
  "forests": "None",
  "hazardous_flora": "Giant_Mantrap",
  "lithoglyphs": "None",
  "power_level": 5,
  "quantum_flux": 2,
  "primary_minerals": "Iron",
  "secondary_minerals": "Compacted_Machinery",
  "ruins": "None",
  "shrine": "None",
  "water": "None",
  "location": {
    "x": 13,
    "y": 98
  }
}