{
  "token_name": "Terraform07349",
  "land_type": "Rocky",
  "alpha_sector": "Arshi_En",
  "activity": "None",
  "atmosphere": "None",
  "bunker": "None",
  "fauna": "Ultrasaurs",
  "forests": "None",
  "hazardous_flora": "None",
  "lithoglyphs": "Lithoglyphs_Red",
  "power_level": 1,
  "quantum_flux": 9,
  "primary_minerals": "None",
  "secondary_minerals": "Gemstones",
  "ruins": "None",
  "shrine": "None",
  "water": "Saltwater_Lake",
  "location": {
    "x": 21,
    "y": 99
  },
  "neighbors": {
    "top": {
      "token_name": "Terraform08531",
      "land_type": "Grass",
      "alpha_sector": "Arshi_En",
      "activity": "None",
      "atmosphere": "None",
      "bunker": "None",
      "fauna": "Livestock",
      "forests": "Palms",
      "hazardous_flora": "Giant_Mantrap",
      "lithoglyphs": "None",
      "power_level": 2,
      "quantum_flux": 4,
      "primary_minerals": "Cardanium",
      "secondary_minerals": "None",
      "ruins": "None",
      "shrine": "None",
      "water": "Funky_Lake",
      "location": {
        "x": 21,
        "y": 100
      }
    },
    "topRight": {
      "token_name": "Terraform05958",
      "land_type": "Fungal",
      "alpha_sector": "Arshi_En",
      "activity": "None",
      "atmosphere": "Prismatic_Motes",
      "bunker": "None",
      "fauna": "Ultrasaurs",
      "forests": "Palms",
      "hazardous_flora": "None",
      "lithoglyphs": "Lithoglyphs_Orange",
      "power_level": 1,
      "quantum_flux": 4,
      "primary_minerals": "Iron",
      "secondary_minerals": "None",
      "ruins": "Alien_Technology_Green",
      "shrine": "None",
      "water": "None",
      "location": {
        "x": 22,
        "y": 100
      }
    },
    "right": {
      "token_name": "Terraform16683",
      "land_type": "Grass",
      "alpha_sector": "Arshi_En",
      "activity": "None",
      "atmosphere": "None",
      "bunker": "Reinforced_Bunker",
      "fauna": "Ultrasaurs",
      "forests": "None",
      "hazardous_flora": "None",
      "lithoglyphs": "Lithoglyphs_Green",
      "power_level": 1,
      "quantum_flux": 4,
      "primary_minerals": "Copper",
      "secondary_minerals": "None",
      "ruins": "None",
      "shrine": "Quantum_Shrine",
      "water": "None",
      "location": {
        "x": 22,
        "y": 99
      }
    },
    "bottomRight": {
      "token_name": "Terraform05716",
      "land_type": "Grass",
      "alpha_sector": "Arshi_En",
      "activity": "Magnetic_Activity",
      "atmosphere": "None",
      "bunker": "None",
      "fauna": "None",
      "forests": "None",
      "hazardous_flora": "Giant_Mantrap",
      "lithoglyphs": "Lithoglyphs_Orange",
      "power_level": 2,
      "quantum_flux": 3,
      "primary_minerals": "Copper",
      "secondary_minerals": "None",
      "ruins": "None",
      "shrine": "None",
      "water": "Freshwater_River",
      "location": {
        "x": 22,
        "y": 98
      }
    },
    "bottom": {
      "token_name": "Terraform05005",
      "land_type": "Rocky",
      "alpha_sector": "Arshi_En",
      "activity": "None",
      "atmosphere": "None",
      "bunker": "None",
      "fauna": "None",
      "forests": "None",
      "hazardous_flora": "Common_Hydra",
      "lithoglyphs": "Lithoglyphs_Green",
      "power_level": 5,
      "quantum_flux": 2,
      "primary_minerals": "None",
      "secondary_minerals": "None",
      "ruins": "None",
      "shrine": "None",
      "water": "Freshwater_Lake",
      "location": {
        "x": 21,
        "y": 98
      }
    },
    "bottonLeft": {
      "token_name": "Terraform09136",
      "land_type": "Tundra",
      "alpha_sector": "Arshi_En",
      "activity": "None",
      "atmosphere": "Prismatic_Motes",
      "bunker": "Reinforced_Bunker",
      "fauna": "Livestock",
      "forests": "None",
      "hazardous_flora": "None",
      "lithoglyphs": "Lithoglyphs_Orange",
      "power_level": 2,
      "quantum_flux": 2,
      "primary_minerals": "Cardanium",
      "secondary_minerals": "Fossils",
      "ruins": "Alien_Technology_Purple",
      "shrine": "None",
      "water": "Freshwater_River",
      "location": {
        "x": 20,
        "y": 98
      }
    },
    "left": {
      "token_name": "Terraform11799",
      "land_type": "Grass",
      "alpha_sector": "Arshi_En",
      "activity": "None",
      "atmosphere": "None",
      "bunker": "Reinforced_Bunker",
      "fauna": "None",
      "forests": "Evergreen",
      "hazardous_flora": "Giant_Mantrap",
      "lithoglyphs": "None",
      "power_level": 1,
      "quantum_flux": 4,
      "primary_minerals": "Copper",
      "secondary_minerals": "None",
      "ruins": "None",
      "shrine": "None",
      "water": "None",
      "location": {
        "x": 20,
        "y": 99
      }
    },
    "topLeft": {
      "token_name": "Terraform09454",
      "land_type": "Wasteland",
      "alpha_sector": "Arshi_En",
      "activity": "Magnetic_Activity",
      "atmosphere": "None",
      "bunker": "Reinforced_Bunker",
      "fauna": "Livestock",
      "forests": "Evergreen",
      "hazardous_flora": "None",
      "lithoglyphs": "None",
      "power_level": 9,
      "quantum_flux": 2,
      "primary_minerals": "None",
      "secondary_minerals": "None",
      "ruins": "Alien_Technology_Purple",
      "shrine": "Solar_Shrine",
      "water": "Toxic_River",
      "location": {
        "x": 20,
        "y": 100
      }
    }
  }
}