{
  "token_name": "Terraform08992",
  "land_type": "Grass",
  "pool_link": "https://pool.pm/c859e9d7e71b8f90bdc1e453fd1b9adbc5e6163898fb574543cb5be8.Terraform08992",
  "image": "https://ipfs.blockfrost.dev/ipfs/QmbWkPbCLRtnaTaqUrh8ykhBes5cXqAVXTwTwRwJhrqWB2",
  "alpha_sector": "Asama",
  "activity": "None",
  "atmosphere": "Prismatic_Motes",
  "bunker": "Quantum_Reinforced_Bunker",
  "fauna": "None",
  "forests": "None",
  "hazardous_flora": "Burning_Mantrap",
  "lithoglyphs": "Lithoglyphs_Blue",
  "power_level": 1,
  "quantum_flux": 1,
  "primary_minerals": "None",
  "secondary_minerals": "None",
  "ruins": "Alien_Technology_Blue",
  "shrine": "None",
  "water": "None",
  "location": {
    "x": 24,
    "y": 87
  },
  "neighbors": {
    "top": {
      "x": 24,
      "y": 88
    },
    "topRight": {
      "x": 25,
      "y": 88
    },
    "right": {
      "x": 25,
      "y": 87
    },
    "bottomRight": {
      "x": 25,
      "y": 86
    },
    "bottom": {
      "x": 24,
      "y": 86
    },
    "bottonLeft": {
      "x": 23,
      "y": 86
    },
    "left": {
      "x": 23,
      "y": 87
    },
    "topLeft": {
      "x": 23,
      "y": 88
    }
  }
}