{
  "token_name": "Terraform15247",
  "land_type": "Grass",
  "pool_link": "https://pool.pm/c859e9d7e71b8f90bdc1e453fd1b9adbc5e6163898fb574543cb5be8.Terraform15247",
  "image": "https://ipfs.blockfrost.dev/ipfs/QmeE1z2225sZcxK8v4zXF7mpLJcuhz9fKPwrhe4o1rUenf",
  "alpha_sector": "Asama",
  "activity": "None",
  "atmosphere": "None",
  "bunker": "Reinforced_Bunker",
  "fauna": "Livestock",
  "forests": "None",
  "hazardous_flora": "Giant_Mantrap",
  "lithoglyphs": "Lithoglyphs_Red",
  "power_level": 3,
  "quantum_flux": 9,
  "primary_minerals": "None",
  "secondary_minerals": "Fossils",
  "ruins": "Alien_Technology_Green",
  "shrine": "None",
  "water": "Cursed_Lake",
  "location": {
    "x": 18,
    "y": 4
  }
}