{
  "token_name": "Terraform14821",
  "land_type": "Artificial",
  "pool_link": "https://pool.pm/c859e9d7e71b8f90bdc1e453fd1b9adbc5e6163898fb574543cb5be8.Terraform14821",
  "image": "https://ipfs.blockfrost.dev/ipfs/QmX4bR6GadCLacwtCUep9pkeoNsLB4ML5sW4Uxkodvsmkp",
  "alpha_sector": "Arshi_En",
  "activity": "None",
  "atmosphere": "None",
  "bunker": "Cardanium_Bunker",
  "fauna": "Critters",
  "forests": "None",
  "hazardous_flora": "Common_Hydra",
  "lithoglyphs": "Lithoglyphs_Green",
  "power_level": 6,
  "quantum_flux": 2,
  "primary_minerals": "Cardanium",
  "secondary_minerals": "None",
  "ruins": "Alien_Technology_Orange",
  "shrine": "Machine_Shrine",
  "water": "None",
  "location": {
    "x": 67,
    "y": 56
  },
  "neighbors": {
    "top": {
      "x": 67,
      "y": 57
    },
    "topRight": {
      "x": 68,
      "y": 57
    },
    "right": {
      "x": 68,
      "y": 56
    },
    "bottomRight": {
      "x": 68,
      "y": 55
    },
    "bottom": {
      "x": 67,
      "y": 55
    },
    "bottonLeft": {
      "x": 66,
      "y": 55
    },
    "left": {
      "x": 66,
      "y": 56
    },
    "topLeft": {
      "x": 66,
      "y": 57
    }
  }
}