{
  "token_name": "Terraform06062",
  "land_type": "Artificial",
  "pool_link": "https://pool.pm/c859e9d7e71b8f90bdc1e453fd1b9adbc5e6163898fb574543cb5be8.Terraform06062",
  "image": "https://ipfs.blockfrost.dev/ipfs/QmU8ydeGMC3p1qkqds1HxN1yRipQ2r39NWSun6opAdDhWW",
  "alpha_sector": "Arshi_En",
  "activity": "None",
  "atmosphere": "Prismatic_Motes",
  "bunker": "None",
  "fauna": "None",
  "forests": "None",
  "hazardous_flora": "Common_Hydra",
  "lithoglyphs": "Lithoglyphs_Green",
  "power_level": 2,
  "quantum_flux": 4,
  "primary_minerals": "Copper",
  "secondary_minerals": "Compacted_Machinery",
  "ruins": "None",
  "shrine": "None",
  "water": "None",
  "location": {
    "x": 7,
    "y": 41
  },
  "neighbors": {
    "top": {
      "x": 7,
      "y": 42
    },
    "topRight": {
      "x": 8,
      "y": 42
    },
    "right": {
      "x": 8,
      "y": 41
    },
    "bottomRight": {
      "x": 8,
      "y": 40
    },
    "bottom": {
      "x": 7,
      "y": 40
    },
    "bottonLeft": {
      "x": 6,
      "y": 40
    },
    "left": {
      "x": 6,
      "y": 41
    },
    "topLeft": {
      "x": 6,
      "y": 42
    }
  }
}