{
  "token_name": "Terraform17615",
  "land_type": "Grass",
  "alpha_sector": "Asama",
  "activity": "None",
  "atmosphere": "Fungal_Spores",
  "bunker": "None",
  "fauna": "Critters",
  "forests": "Evergreen",
  "hazardous_flora": "Common_Hydra",
  "lithoglyphs": "Lithoglyphs_Blue",
  "power_level": 6,
  "quantum_flux": 7,
  "primary_minerals": "Iron",
  "secondary_minerals": "None",
  "ruins": "Alien_Technology_Blue",
  "shrine": "None",
  "water": "Cursed_River",
  "location": {
    "x": 61,
    "y": 17
  },
  "neighbors": {
    "top": {},
    "topRight": {},
    "right": {},
    "bottomRight": {},
    "bottom": {},
    "bottonLeft": {},
    "left": {},
    "topLeft": {}
  }
}