{
  "token_name": "Terraform05683",
  "land_type": "Grass",
  "pool_link": "https://pool.pm/c859e9d7e71b8f90bdc1e453fd1b9adbc5e6163898fb574543cb5be8.Terraform05683",
  "image": "https://ipfs.blockfrost.dev/ipfs/QmbFD3GE8bTLHxKuiVFnhBWNNCN31Mvn4RThxnftXRcriV",
  "alpha_sector": "Arshi_En",
  "activity": "None",
  "atmosphere": "Fungal_Spores",
  "bunker": "None",
  "fauna": "None",
  "forests": "Prismaleaf",
  "hazardous_flora": "Giant_Mantrap",
  "lithoglyphs": "None",
  "power_level": 9,
  "quantum_flux": 5,
  "primary_minerals": "None",
  "secondary_minerals": "Fossils",
  "ruins": "Alien_Technology_Green",
  "shrine": "None",
  "water": "None",
  "location": {
    "x": 25,
    "y": 35
  }
}