{
  "token_name": "Terraform02656",
  "land_type": "Tundra",
  "alpha_sector": "Asama",
  "activity": "None",
  "atmosphere": "None",
  "bunker": "Reinforced_Bunker",
  "fauna": "None",
  "forests": "Evergreen",
  "hazardous_flora": "Melodious_Mantrap",
  "lithoglyphs": "Lithoglyphs_Green",
  "power_level": 3,
  "quantum_flux": 3,
  "primary_minerals": "None",
  "secondary_minerals": "None",
  "ruins": "None",
  "shrine": "None",
  "water": "Cursed_Lake",
  "location": {
    "x": 42,
    "y": 17
  },
  "neighbors": {
    "top": {},
    "topRight": {},
    "right": {},
    "bottomRight": {},
    "bottom": {},
    "bottonLeft": {},
    "left": {},
    "topLeft": {}
  }
}