{
  "token_name": "Terraform09557",
  "land_type": "Grass",
  "alpha_sector": "Asama",
  "activity": "None",
  "atmosphere": "Fungal_Spores",
  "bunker": "None",
  "fauna": "Critters",
  "forests": "None",
  "hazardous_flora": "Fungal_Hydra",
  "lithoglyphs": "None",
  "power_level": 2,
  "quantum_flux": 4,
  "primary_minerals": "None",
  "secondary_minerals": "None",
  "ruins": "None",
  "shrine": "None",
  "water": "None",
  "location": {
    "x": 99,
    "y": 78
  },
  "neighbors": {
    "top": {},
    "topRight": {},
    "right": {},
    "bottomRight": {},
    "bottom": {},
    "bottonLeft": {},
    "left": {},
    "topLeft": {}
  }
}