{
  "token_name": "Terraform03763",
  "land_type": "Grass",
  "pool_link": "https://pool.pm/c859e9d7e71b8f90bdc1e453fd1b9adbc5e6163898fb574543cb5be8.Terraform03763",
  "image": "https://ipfs.blockfrost.dev/ipfs/QmamhR9aGf24hdvbVZb4xBww2D7bfomibStEuu8fLytywk",
  "alpha_sector": "Arshi_En",
  "activity": "None",
  "atmosphere": "None",
  "bunker": "None",
  "fauna": "Livestock",
  "forests": "None",
  "hazardous_flora": "Common_Hydra",
  "lithoglyphs": "Lithoglyphs_Timelost",
  "power_level": 2,
  "quantum_flux": 3,
  "primary_minerals": "Copper",
  "secondary_minerals": "None",
  "ruins": "None",
  "shrine": "None",
  "water": "Freshwater_Lake",
  "location": {
    "x": 69,
    "y": 76
  }
}