{
  "token_name": "Terraform00855",
  "land_type": "Grass",
  "pool_link": "https://pool.pm/c859e9d7e71b8f90bdc1e453fd1b9adbc5e6163898fb574543cb5be8.Terraform00855",
  "image": "https://ipfs.blockfrost.dev/ipfs/QmP8S25Ch6VaojwVDujToxmfaDX5wkBf9pNLDD9yViKfzK",
  "alpha_sector": "Asama",
  "activity": "None",
  "atmosphere": "Fungal_Spores",
  "bunker": "None",
  "fauna": "None",
  "forests": "None",
  "hazardous_flora": "Giant_Mantrap",
  "lithoglyphs": "Lithoglyphs_Orange",
  "power_level": 4,
  "quantum_flux": 3,
  "primary_minerals": "Cardanium",
  "secondary_minerals": "None",
  "ruins": "None",
  "shrine": "Fungal_Shrine",
  "water": "None",
  "location": {
    "x": 44,
    "y": 64
  }
}